edurag/__init__.py
edurag/config.py
edurag/core/__init__.py
edurag/core/agentic_rag.py
edurag/core/simple_rag.py
edurag/document/__init__.py
edurag/document/loader.py
edurag/document/splitter.py
edurag/llm/__init__.py
edurag/llm/provider.py
edurag/prompt/__init__.py
edurag/prompt/teacher_profile.py
edurag/vectorstore/__init__.py
edurag/vectorstore/faiss_store.py
edurag-0.1.3.dist-info/METADATA
edurag-0.1.3.dist-info/WHEEL
edurag-0.1.3.dist-info/licenses/LICENSE
edurag-0.1.3.dist-info/RECORD
