Metadata-Version: 2.4
Name: edurag
Version: 0.1.3
Summary: An LLM-based Retrieval-Augmented Generation (RAG) component for education, supporting problem solving, academic literature analysis, and knowledge Q&A.
Project-URL: Homepage, https://github.com/edurag/edurag
Project-URL: Documentation, https://github.com/edurag/edurag#readme
Project-URL: Repository, https://github.com/edurag/edurag
Project-URL: Issues, https://github.com/edurag/edurag/issues
Author: EduRAG Team
License: MIT
License-File: LICENSE
Keywords: AI,LLM,RAG,education,langchain,retrieval-augmented-generation
Classifier: Development Status :: 3 - Alpha
Classifier: Intended Audience :: Developers
Classifier: Intended Audience :: Education
Classifier: License :: OSI Approved :: MIT License
Classifier: Programming Language :: Python :: 3.10
Classifier: Programming Language :: Python :: 3.11
Classifier: Programming Language :: Python :: 3.12
Classifier: Topic :: Education
Classifier: Topic :: Scientific/Engineering :: Artificial Intelligence
Requires-Python: >=3.10
Requires-Dist: docx2txt>=0.8
Requires-Dist: faiss-cpu>=1.8.0
Requires-Dist: langchain-classic>=0.3.0
Requires-Dist: langchain-community>=0.3.0
Requires-Dist: langchain-openai>=0.2.0
Requires-Dist: langchain-text-splitters>=0.3.0
Requires-Dist: langchain>=0.3.0
Requires-Dist: pypdf>=4.0.0
Provides-Extra: agentic
Requires-Dist: langgraph>=0.2.0; extra == 'agentic'
Provides-Extra: all
Requires-Dist: langchain-google-genai>=2.0.0; extra == 'all'
Requires-Dist: langchain-ollama>=0.2.0; extra == 'all'
Requires-Dist: langgraph>=0.2.0; extra == 'all'
Provides-Extra: dev
Requires-Dist: mypy>=1.10.0; extra == 'dev'
Requires-Dist: pytest-cov>=4.0.0; extra == 'dev'
Requires-Dist: pytest>=8.0.0; extra == 'dev'
Requires-Dist: ruff>=0.4.0; extra == 'dev'
Provides-Extra: gemini
Requires-Dist: langchain-google-genai>=2.0.0; extra == 'gemini'
Provides-Extra: ollama
Requires-Dist: langchain-ollama>=0.2.0; extra == 'ollama'
